mx_recordio/__init__.py
mx_recordio/base.py
mx_recordio/libinfo.py
mx_recordio/recordio.py
mx_recordio-0.2.dist-info/LICENSE
mx_recordio-0.2.dist-info/METADATA
mx_recordio-0.2.dist-info/WHEEL
mx_recordio-0.2.dist-info/top_level.txt
mx_recordio-0.2.dist-info/RECORD
