Metadata-Version: 2.1
Name: mx_recordio
Version: 0.2
License-File: LICENSE
Requires-Dist: numpy <2.0,>=1.20.0
